trame/__init__.py
trame/modules/__init__.py
trame/modules/alerts.py
trame/modules/alerts_quasar.py
trame/modules/alerts_vuetify.py
trame/widgets/__init__.py
trame/widgets/alerts.py
trame/widgets/alerts_quasar.py
trame/widgets/alerts_vuetify.py
trame_alerts/__init__.py
trame_alerts/core/__init__.py
trame_alerts/core/service.py
trame_alerts/core/widgets.py
trame_alerts/core/module/__init__.py
trame_alerts/core/module/serve/trame_alerts.umd.js
trame_alerts/core/module/serve/trame_alerts.umd.js.map
trame_alerts/quasar/__init__.py
trame_alerts/quasar/widgets.py
trame_alerts/quasar/module/__init__.py
trame_alerts/quasar/module/serve/trame_alerts_quasar.css
trame_alerts/quasar/module/serve/trame_alerts_quasar.umd.js
trame_alerts/vuetify/__init__.py
trame_alerts/vuetify/widgets.py
trame_alerts/vuetify/module/__init__.py
trame_alerts/vuetify/module/serve/trame_alerts_vuetify.css
trame_alerts/vuetify/module/serve/trame_alerts_vuetify.umd.js
trame_alerts-0.2.0.dist-info/LICENSE
trame_alerts-0.2.0.dist-info/METADATA
trame_alerts-0.2.0.dist-info/WHEEL
trame_alerts-0.2.0.dist-info/top_level.txt
trame_alerts-0.2.0.dist-info/RECORD
