Metadata-Version: 2.2
Name: trame-alerts
Version: 0.2.0
Summary: A trame package to manage and display alerts
Author: Alessandro Genova
License: Apache Software License
Keywords: Python,Interactive,Web,Application,Framework
Classifier: Development Status :: 5 - Production/Stable
Classifier: Environment :: Web Environment
Classifier: License :: OSI Approved :: Apache Software License
Classifier: Natural Language :: English
Classifier: Operating System :: OS Independent
Classifier: Programming Language :: Python :: 3 :: Only
Classifier: Topic :: Software Development :: Libraries :: Application Frameworks
Classifier: Topic :: Software Development :: Libraries :: Python Modules
Requires-Python: >=3.9
License-File: LICENSE
Requires-Dist: trame_client>=3.5
Requires-Dist: trame_server>=3.3
Provides-Extra: dev
Requires-Dist: pre-commit; extra == "dev"
Requires-Dist: ruff; extra == "dev"
Requires-Dist: pytest; extra == "dev"
Requires-Dist: codespell; extra == "dev"
Provides-Extra: quasar
Requires-Dist: trame_quasar; extra == "quasar"
Provides-Extra: vuetify
Requires-Dist: trame_vuetify; extra == "vuetify"
